OT1D.cp39-win_amd64.pyd
OT1D-0.3.6.dist-info/LICENSE
OT1D-0.3.6.dist-info/METADATA
OT1D-0.3.6.dist-info/WHEEL
OT1D-0.3.6.dist-info/top_level.txt
OT1D-0.3.6.dist-info/RECORD
