Metadata-Version: 2.1
Name: OT1D
Version: 0.3.6
Summary: Discrete Optimal Transport in 1D by Linear Programming
Home-page: https://github.com/stegua/ot1d
Author: Stefano Gualandi
Author-email: stefano.gualandi@gmail.com
License: UNKNOWN
Platform: linux
Platform: macosx
Platform: windows
